gchatbot/__init__.py
gchatbot/main.py
gchatbot/parser.py
gchatbot/processor.py
gchatbot/response.py
gchatbot/types.py
gchatbot-0.3.1.dist-info/licenses/LICENSE
gchatbot-0.3.1.dist-info/METADATA
gchatbot-0.3.1.dist-info/WHEEL
gchatbot-0.3.1.dist-info/top_level.txt
gchatbot-0.3.1.dist-info/RECORD
