Metadata-Version: 2.4
Name: gchatbot
Version: 0.3.1
Summary: A modern Python library for building Google Chat bots with serverless-safe async processing.
Home-page: https://github.com/guilhermecf10/gchatbot
Author: João Matheus & Guilherme Fialho
Author-email: guilhermec.fialho@gmail.com
License: MIT
Project-URL: Bug Reports, https://github.com/guilhermecf10/gchatbot/issues
Project-URL: Source, https://github.com/guilhermecf10/gchatbot
Project-URL: Documentation, https://github.com/guilhermecf10/gchatbot#readme
Keywords: google-chat,chatbot,bot,google-workspace,fastapi,async,serverless,progressive-responses,hybrid-sync-async
Classifier: Development Status :: 4 - Beta
Classifier: Intended Audience :: Developers
Classifier: Topic :: Communications :: Chat
Classifier: Topic :: Software Development :: Libraries :: Python Modules
Classifier: Programming Language :: Python :: 3
Classifier: Programming Language :: Python :: 3.7
Classifier: Programming Language :: Python :: 3.8
Classifier: Programming Language :: Python :: 3.9
Classifier: Programming Language :: Python :: 3.10
Classifier: Programming Language :: Python :: 3.11
Classifier: Programming Language :: Python :: 3.12
Classifier: License :: OSI Approved :: MIT License
Classifier: Operating System :: OS Independent
Classifier: Framework :: FastAPI
Requires-Python: >=3.7
License-File: LICENSE
Requires-Dist: google-auth>=2.0.0
Requires-Dist: google-api-python-client>=2.0.0
Requires-Dist: google-apps-chat>=0.1.0
Requires-Dist: protobuf>=3.19.0
Provides-Extra: fastapi
Requires-Dist: fastapi>=0.70.0; extra == "fastapi"
Requires-Dist: uvicorn>=0.15.0; extra == "fastapi"
Provides-Extra: async
Requires-Dist: aiohttp>=3.8.0; extra == "async"
Requires-Dist: asyncio-throttle>=1.0.0; extra == "async"
Provides-Extra: dev
Requires-Dist: pytest>=6.0.0; extra == "dev"
Requires-Dist: pytest-asyncio>=0.18.0; extra == "dev"
Requires-Dist: black>=22.0.0; extra == "dev"
Requires-Dist: isort>=5.0.0; extra == "dev"
Requires-Dist: mypy>=0.900; extra == "dev"
Provides-Extra: all
Requires-Dist: fastapi>=0.70.0; extra == "all"
Requires-Dist: uvicorn>=0.15.0; extra == "all"
Requires-Dist: aiohttp>=3.8.0; extra == "all"
Requires-Dist: asyncio-throttle>=1.0.0; extra == "all"
Dynamic: author
Dynamic: author-email
Dynamic: classifier
Dynamic: description
Dynamic: description-content-type
Dynamic: home-page
Dynamic: keywords
Dynamic: license
Dynamic: license-file
Dynamic: project-url
Dynamic: provides-extra
Dynamic: requires-dist
Dynamic: requires-python
Dynamic: summary
